[
	{
		"Time": "2021-07-17T02:00:00+02:00",
		"Open": 0.48931,
		"High": 0.492,
		"Low": 0.42294,
		"Close": 0.44804,
		"Volume": 113012909.9
	},
	{
		"Time": "2021-07-16T02:00:00+02:00",
		"Open": 0.54298,
		"High": 0.60621,
		"Low": 0.47732,
		"Close": 0.48934,
		"Volume": 169664640.9
	},
	{
		"Time": "2021-07-15T02:00:00+02:00",
		"Open": 0.59129,
		"High": 0.692,
		"Low": 0.51351,
		"Close": 0.54367,
		"Volume": 432643113.3
	},
	{
		"Time": "2021-07-14T02:00:00+02:00",
		"Open": 0.43395,
		"High": 0.6196,
		"Low": 0.38269,
		"Close": 0.59047,
		"Volume": 336266866.2
	},
	{
		"Time": "2021-07-13T02:00:00+02:00",
		"Open": 0.41766,
		"High": 0.46837,
		"Low": 0.4075,
		"Close": 0.43383,
		"Volume": 145121654.1
	},
	{
		"Time": "2021-07-12T02:00:00+02:00",
		"Open": 0.48996,
		"High": 0.49097,
		"Low": 0.41672,
		"Close": 0.41746,
		"Volume": 89924856.3
	},
	{
		"Time": "2021-07-11T02:00:00+02:00",
		"Open": 0.49185,
		"High": 0.5055,
		"Low": 0.45358,
		"Close": 0.48959,
		"Volume": 106189156.1
	},
	{
		"Time": "2021-07-10T02:00:00+02:00",
		"Open": 0.49375,
		"High": 0.5449,
		"Low": 0.46053,
		"Close": 0.49122,
		"Volume": 257914699.1
	},
	{
		"Time": "2021-07-09T02:00:00+02:00",
		"Open": 0.42652,
		"High": 0.515,
		"Low": 0.37019,
		"Close": 0.49305,
		"Volume": 277564776.6
	},
	{
		"Time": "2021-07-08T02:00:00+02:00",
		"Open": 0.40048,
		"High": 0.53725,
		"Low": 0.38414,
		"Close": 0.427,
		"Volume": 405240462.9
	},
	{
		"Time": "2021-07-07T02:00:00+02:00",
		"Open": 0.30937,
		"High": 0.44645,
		"Low": 0.3081,
		"Close": 0.40047,
		"Volume": 246885539.8
	},
	{
		"Time": "2021-07-06T02:00:00+02:00",
		"Open": 0.26681,
		"High": 0.34,
		"Low": 0.26619,
		"Close": 0.30937,
		"Volume": 123565308.9
	},
	{
		"Time": "2021-07-05T02:00:00+02:00",
		"Open": 0.27598,
		"High": 0.28841,
		"Low": 0.25704,
		"Close": 0.26657,
		"Volume": 46710663
	},
	{
		"Time": "2021-07-04T02:00:00+02:00",
		"Open": 0.26457,
		"High": 0.3022,
		"Low": 0.25481,
		"Close": 0.2763,
		"Volume": 74023379
	},
	{
		"Time": "2021-07-03T02:00:00+02:00",
		"Open": 0.24438,
		"High": 0.27457,
		"Low": 0.23482,
		"Close": 0.26456,
		"Volume": 41876313.1
	},
	{
		"Time": "2021-07-02T02:00:00+02:00",
		"Open": 0.2518,
		"High": 0.26,
		"Low": 0.2216,
		"Close": 0.244,
		"Volume": 40999073.6
	},
	{
		"Time": "2021-07-01T02:00:00+02:00",
		"Open": 0.24511,
		"High": 0.273,
		"Low": 0.23905,
		"Close": 0.25238,
		"Volume": 88647046
	},
	{
		"Time": "2021-06-30T02:00:00+02:00",
		"Open": 0.22686,
		"High": 0.24687,
		"Low": 0.21175,
		"Close": 0.24488,
		"Volume": 52138783
	},
	{
		"Time": "2021-06-29T02:00:00+02:00",
		"Open": 0.20428,
		"High": 0.22938,
		"Low": 0.20247,
		"Close": 0.22686,
		"Volume": 35497233.7
	},
	{
		"Time": "2021-06-28T02:00:00+02:00",
		"Open": 0.1901,
		"High": 0.21,
		"Low": 0.18807,
		"Close": 0.20416,
		"Volume": 26533629.9
	},
	{
		"Time": "2021-06-27T02:00:00+02:00",
		"Open": 0.18428,
		"High": 0.19038,
		"Low": 0.17637,
		"Close": 0.19002,
		"Volume": 15353854.1
	},
	{
		"Time": "2021-06-26T02:00:00+02:00",
		"Open": 0.18296,
		"High": 0.1892,
		"Low": 0.1705,
		"Close": 0.18434,
		"Volume": 16979557.5
	},
	{
		"Time": "2021-06-25T02:00:00+02:00",
		"Open": 0.2035,
		"High": 0.21155,
		"Low": 0.18118,
		"Close": 0.18341,
		"Volume": 34415874.4
	},
	{
		"Time": "2021-06-24T02:00:00+02:00",
		"Open": 0.1923,
		"High": 0.21164,
		"Low": 0.17979,
		"Close": 0.2031,
		"Volume": 34839969.5
	},
	{
		"Time": "2021-06-23T02:00:00+02:00",
		"Open": 0.17443,
		"High": 0.2091,
		"Low": 0.16656,
		"Close": 0.19251,
		"Volume": 55557777.5
	},
	{
		"Time": "2021-06-22T02:00:00+02:00",
		"Open": 0.17875,
		"High": 0.19365,
		"Low": 0.14661,
		"Close": 0.17405,
		"Volume": 60969572.8
	},
	{
		"Time": "2021-06-21T02:00:00+02:00",
		"Open": 0.23806,
		"High": 0.23959,
		"Low": 0.17769,
		"Close": 0.17928,
		"Volume": 42726011
	},
	{
		"Time": "2021-06-20T02:00:00+02:00",
		"Open": 0.24572,
		"High": 0.24885,
		"Low": 0.22051,
		"Close": 0.23806,
		"Volume": 19025532.3
	},
	{
		"Time": "2021-06-19T02:00:00+02:00",
		"Open": 0.25596,
		"High": 0.25799,
		"Low": 0.24512,
		"Close": 0.24567,
		"Volume": 10795774.2
	},
	{
		"Time": "2021-06-18T02:00:00+02:00",
		"Open": 0.2716,
		"High": 0.27348,
		"Low": 0.24204,
		"Close": 0.25648,
		"Volume": 16214930.2
	},
	{
		"Time": "2021-06-17T02:00:00+02:00",
		"Open": 0.2705,
		"High": 0.28679,
		"Low": 0.26521,
		"Close": 0.27156,
		"Volume": 18658030.4
	},
	{
		"Time": "2021-06-16T02:00:00+02:00",
		"Open": 0.28643,
		"High": 0.30086,
		"Low": 0.26633,
		"Close": 0.27045,
		"Volume": 42584179.1
	},
	{
		"Time": "2021-06-15T02:00:00+02:00",
		"Open": 0.2842,
		"High": 0.28997,
		"Low": 0.27248,
		"Close": 0.28643,
		"Volume": 23380697.8
	},
	{
		"Time": "2021-06-14T02:00:00+02:00",
		"Open": 0.27714,
		"High": 0.28466,
		"Low": 0.26843,
		"Close": 0.28451,
		"Volume": 22161873.2
	},
	{
		"Time": "2021-06-13T02:00:00+02:00",
		"Open": 0.26295,
		"High": 0.27804,
		"Low": 0.25358,
		"Close": 0.27672,
		"Volume": 20373281.8
	},
	{
		"Time": "2021-06-12T02:00:00+02:00",
		"Open": 0.30685,
		"High": 0.30855,
		"Low": 0.25524,
		"Close": 0.26276,
		"Volume": 47798630.5
	},
	{
		"Time": "2021-06-11T02:00:00+02:00",
		"Open": 0.3001,
		"High": 0.34333,
		"Low": 0.28283,
		"Close": 0.30683,
		"Volume": 77317144.3
	},
	{
		"Time": "2021-06-10T02:00:00+02:00",
		"Open": 0.29157,
		"High": 0.30551,
		"Low": 0.27634,
		"Close": 0.29957,
		"Volume": 28774494.8
	},
	{
		"Time": "2021-06-09T02:00:00+02:00",
		"Open": 0.28104,
		"High": 0.29157,
		"Low": 0.26256,
		"Close": 0.29155,
		"Volume": 27495054.3
	},
	{
		"Time": "2021-06-08T02:00:00+02:00",
		"Open": 0.29484,
		"High": 0.30053,
		"Low": 0.25002,
		"Close": 0.28129,
		"Volume": 31395767.4
	},
	{
		"Time": "2021-06-07T02:00:00+02:00",
		"Open": 0.32482,
		"High": 0.33154,
		"Low": 0.29079,
		"Close": 0.29493,
		"Volume": 16698141.3
	},
	{
		"Time": "2021-06-06T02:00:00+02:00",
		"Open": 0.31766,
		"High": 0.33145,
		"Low": 0.31567,
		"Close": 0.32491,
		"Volume": 15421278.9
	},
	{
		"Time": "2021-06-05T02:00:00+02:00",
		"Open": 0.33297,
		"High": 0.34539,
		"Low": 0.30942,
		"Close": 0.318,
		"Volume": 19648283.3
	},
	{
		"Time": "2021-06-04T02:00:00+02:00",
		"Open": 0.36357,
		"High": 0.37,
		"Low": 0.30515,
		"Close": 0.33305,
		"Volume": 37196395.4
	},
	{
		"Time": "2021-06-03T02:00:00+02:00",
		"Open": 0.33185,
		"High": 0.36971,
		"Low": 0.32068,
		"Close": 0.36357,
		"Volume": 39142396.4
	},
	{
		"Time": "2021-06-02T02:00:00+02:00",
		"Open": 0.32309,
		"High": 0.33899,
		"Low": 0.31211,
		"Close": 0.33164,
		"Volume": 27547915.4
	},
	{
		"Time": "2021-06-01T02:00:00+02:00",
		"Open": 0.33384,
		"High": 0.33433,
		"Low": 0.31019,
		"Close": 0.32346,
		"Volume": 23867930.8
	},
	{
		"Time": "2021-05-31T02:00:00+02:00",
		"Open": 0.31556,
		"High": 0.335,
		"Low": 0.29383,
		"Close": 0.33413,
		"Volume": 29356407.3
	},
	{
		"Time": "2021-05-30T02:00:00+02:00",
		"Open": 0.30537,
		"High": 0.33531,
		"Low": 0.28036,
		"Close": 0.31571,
		"Volume": 29651948.4
	},
	{
		"Time": "2021-05-29T02:00:00+02:00",
		"Open": 0.33741,
		"High": 0.33845,
		"Low": 0.28326,
		"Close": 0.3053,
		"Volume": 41983027.4
	},
	{
		"Time": "2021-05-28T02:00:00+02:00",
		"Open": 0.33836,
		"High": 0.38361,
		"Low": 0.30343,
		"Close": 0.3378,
		"Volume": 103799479.5
	},
	{
		"Time": "2021-05-27T02:00:00+02:00",
		"Open": 0.37145,
		"High": 0.3768,
		"Low": 0.32557,
		"Close": 0.33732,
		"Volume": 56066629.1
	},
	{
		"Time": "2021-05-26T02:00:00+02:00",
		"Open": 0.29296,
		"High": 0.38739,
		"Low": 0.28235,
		"Close": 0.37144,
		"Volume": 88785330
	},
	{
		"Time": "2021-05-25T02:00:00+02:00",
		"Open": 0.312,
		"High": 0.3207,
		"Low": 0.26156,
		"Close": 0.29254,
		"Volume": 64392512.3
	},
	{
		"Time": "2021-05-24T02:00:00+02:00",
		"Open": 0.29331,
		"High": 0.31973,
		"Low": 0.25675,
		"Close": 0.31132,
		"Volume": 110441048.2
	},
	{
		"Time": "2021-05-23T02:00:00+02:00",
		"Open": 0.44213,
		"High": 0.47447,
		"Low": 0.23431,
		"Close": 0.29331,
		"Volume": 271482850.2
	},
	{
		"Time": "2021-05-22T02:00:00+02:00",
		"Open": 0.29152,
		"High": 0.47974,
		"Low": 0.27347,
		"Close": 0.44215,
		"Volume": 384918247.9
	},
	{
		"Time": "2021-05-21T02:00:00+02:00",
		"Open": 0.31052,
		"High": 0.3539,
		"Low": 0.23702,
		"Close": 0.29284,
		"Volume": 84433028.1
	},
	{
		"Time": "2021-05-20T02:00:00+02:00",
		"Open": 0.24701,
		"High": 0.31603,
		"Low": 0.21389,
		"Close": 0.31066,
		"Volume": 65039301.4
	},
	{
		"Time": "2021-05-19T02:00:00+02:00",
		"Open": 0.39225,
		"High": 0.40178,
		"Low": 0.17327,
		"Close": 0.24651,
		"Volume": 91903410.3
	},
	{
		"Time": "2021-05-18T02:00:00+02:00",
		"Open": 0.37595,
		"High": 0.41988,
		"Low": 0.37,
		"Close": 0.39225,
		"Volume": 40996993.4
	},
	{
		"Time": "2021-05-17T02:00:00+02:00",
		"Open": 0.41567,
		"High": 0.41622,
		"Low": 0.35694,
		"Close": 0.3756,
		"Volume": 54432422.2
	},
	{
		"Time": "2021-05-16T02:00:00+02:00",
		"Open": 0.43321,
		"High": 0.46733,
		"Low": 0.39,
		"Close": 0.41585,
		"Volume": 46431957.7
	},
	{
		"Time": "2021-05-15T02:00:00+02:00",
		"Open": 0.44004,
		"High": 0.5133,
		"Low": 0.42969,
		"Close": 0.43278,
		"Volume": 71532761.3
	},
	{
		"Time": "2021-05-14T02:00:00+02:00",
		"Open": 0.42325,
		"High": 0.45937,
		"Low": 0.41,
		"Close": 0.44066,
		"Volume": 29087300.9
	},
	{
		"Time": "2021-05-13T02:00:00+02:00",
		"Open": 0.41143,
		"High": 0.44989,
		"Low": 0.38827,
		"Close": 0.42325,
		"Volume": 48280621.2
	},
	{
		"Time": "2021-05-12T02:00:00+02:00",
		"Open": 0.50305,
		"High": 0.53337,
		"Low": 0.40122,
		"Close": 0.41143,
		"Volume": 33270899.7
	},
	{
		"Time": "2021-05-11T02:00:00+02:00",
		"Open": 0.46148,
		"High": 0.51304,
		"Low": 0.44961,
		"Close": 0.5028,
		"Volume": 27344555.5
	},
	{
		"Time": "2021-05-10T02:00:00+02:00",
		"Open": 0.54313,
		"High": 0.54916,
		"Low": 0.43,
		"Close": 0.46207,
		"Volume": 31926590.7
	},
	{
		"Time": "2021-05-09T02:00:00+02:00",
		"Open": 0.543,
		"High": 0.54958,
		"Low": 0.50116,
		"Close": 0.54303,
		"Volume": 23023342.1
	},
	{
		"Time": "2021-05-08T02:00:00+02:00",
		"Open": 0.5465,
		"High": 0.57292,
		"Low": 0.53419,
		"Close": 0.543,
		"Volume": 19673010.5
	},
	{
		"Time": "2021-05-07T02:00:00+02:00",
		"Open": 0.56172,
		"High": 0.58039,
		"Low": 0.52157,
		"Close": 0.54686,
		"Volume": 31187582.4
	},
	{
		"Time": "2021-05-06T02:00:00+02:00",
		"Open": 0.60446,
		"High": 0.60687,
		"Low": 0.53554,
		"Close": 0.56196,
		"Volume": 35780145.8
	},
	{
		"Time": "2021-05-05T02:00:00+02:00",
		"Open": 0.57437,
		"High": 0.61976,
		"Low": 0.56525,
		"Close": 0.60431,
		"Volume": 42656774.5
	},
	{
		"Time": "2021-05-04T02:00:00+02:00",
		"Open": 0.65682,
		"High": 0.72895,
		"Low": 0.57214,
		"Close": 0.57294,
		"Volume": 141704402.6
	},
	{
		"Time": "2021-05-03T02:00:00+02:00",
		"Open": 0.58181,
		"High": 0.679,
		"Low": 0.57,
		"Close": 0.6569,
		"Volume": 67389837.5
	},
	{
		"Time": "2021-05-02T02:00:00+02:00",
		"Open": 0.60314,
		"High": 0.606,
		"Low": 0.55607,
		"Close": 0.58192,
		"Volume": 20375360.1
	},
	{
		"Time": "2021-05-01T02:00:00+02:00",
		"Open": 0.6211,
		"High": 0.6295,
		"Low": 0.59121,
		"Close": 0.60314,
		"Volume": 20726175.9
	},
	{
		"Time": "2021-04-30T02:00:00+02:00",
		"Open": 0.56449,
		"High": 0.63214,
		"Low": 0.55036,
		"Close": 0.6211,
		"Volume": 45729915.3
	},
	{
		"Time": "2021-04-29T02:00:00+02:00",
		"Open": 0.58985,
		"High": 0.61104,
		"Low": 0.53952,
		"Close": 0.56495,
		"Volume": 38334480
	},
	{
		"Time": "2021-04-28T02:00:00+02:00",
		"Open": 0.5407,
		"High": 0.61548,
		"Low": 0.51276,
		"Close": 0.58983,
		"Volume": 69811625.3
	},
	{
		"Time": "2021-04-27T02:00:00+02:00",
		"Open": 0.49994,
		"High": 0.549,
		"Low": 0.48579,
		"Close": 0.54047,
		"Volume": 22633420.6
	},
	{
		"Time": "2021-04-26T02:00:00+02:00",
		"Open": 0.41791,
		"High": 0.5008,
		"Low": 0.4129,
		"Close": 0.49995,
		"Volume": 34128712.2
	},
	{
		"Time": "2021-04-25T02:00:00+02:00",
		"Open": 0.410377,
		"High": 0.4542,
		"Low": 0.391,
		"Close": 0.41792,
		"Volume": 28482098.9
	},
	{
		"Time": "2021-04-24T02:00:00+02:00",
		"Open": 0.427291,
		"High": 0.44,
		"Low": 0.391339,
		"Close": 0.411661,
		"Volume": 38463049
	},
	{
		"Time": "2021-04-23T02:00:00+02:00",
		"Open": 0.437008,
		"High": 0.449438,
		"Low": 0.335308,
		"Close": 0.427283,
		"Volume": 72861784
	},
	{
		"Time": "2021-04-22T02:00:00+02:00",
		"Open": 0.510109,
		"High": 0.528987,
		"Low": 0.429677,
		"Close": 0.4379,
		"Volume": 47721615
	},
	{
		"Time": "2021-04-21T02:00:00+02:00",
		"Open": 0.523641,
		"High": 0.5769,
		"Low": 0.503,
		"Close": 0.510387,
		"Volume": 43411572
	},
	{
		"Time": "2021-04-20T02:00:00+02:00",
		"Open": 0.514202,
		"High": 0.533602,
		"Low": 0.448689,
		"Close": 0.522991,
		"Volume": 48621221
	},
	{
		"Time": "2021-04-19T02:00:00+02:00",
		"Open": 0.561992,
		"High": 0.578583,
		"Low": 0.50515,
		"Close": 0.51389,
		"Volume": 31716094
	},
	{
		"Time": "2021-04-18T02:00:00+02:00",
		"Open": 0.660765,
		"High": 0.668589,
		"Low": 0.462204,
		"Close": 0.561063,
		"Volume": 58031909
	},
	{
		"Time": "2021-04-17T02:00:00+02:00",
		"Open": 0.703876,
		"High": 0.71,
		"Low": 0.64404,
		"Close": 0.660767,
		"Volume": 39087816
	},
	{
		"Time": "2021-04-16T02:00:00+02:00",
		"Open": 0.682465,
		"High": 0.71,
		"Low": 0.621051,
		"Close": 0.703877,
		"Volume": 50659501
	},
	{
		"Time": "2021-04-15T02:00:00+02:00",
		"Open": 0.645903,
		"High": 0.698936,
		"Low": 0.642986,
		"Close": 0.681807,
		"Volume": 26021058
	},
	{
		"Time": "2021-04-14T02:00:00+02:00",
		"Open": 0.669382,
		"High": 0.671487,
		"Low": 0.61351,
		"Close": 0.64535,
		"Volume": 27264175
	},
	{
		"Time": "2021-04-13T02:00:00+02:00",
		"Open": 0.687343,
		"High": 0.712,
		"Low": 0.644234,
		"Close": 0.669381,
		"Volume": 40379518
	},
	{
		"Time": "2021-04-12T02:00:00+02:00",
		"Open": 0.640998,
		"High": 0.708302,
		"Low": 0.631397,
		"Close": 0.687396,
		"Volume": 47936976
	},
	{
		"Time": "2021-04-11T02:00:00+02:00",
		"Open": 0.66399,
		"High": 0.677,
		"Low": 0.615416,
		"Close": 0.641819,
		"Volume": 36809307
	},
	{
		"Time": "2021-04-10T02:00:00+02:00",
		"Open": 0.698658,
		"High": 0.700435,
		"Low": 0.637129,
		"Close": 0.66399,
		"Volume": 41377764
	},
	{
		"Time": "2021-04-09T02:00:00+02:00",
		"Open": 0.684199,
		"High": 0.749999,
		"Low": 0.660795,
		"Close": 0.698661,
		"Volume": 78443838
	},
	{
		"Time": "2021-04-08T02:00:00+02:00",
		"Open": 0.633428,
		"High": 0.705796,
		"Low": 0.6,
		"Close": 0.684806,
		"Volume": 68424381
	},
	{
		"Time": "2021-04-07T02:00:00+02:00",
		"Open": 0.636077,
		"High": 0.655355,
		"Low": 0.53,
		"Close": 0.632097,
		"Volume": 83805865
	},
	{
		"Time": "2021-04-06T02:00:00+02:00",
		"Open": 0.671463,
		"High": 0.68199,
		"Low": 0.601874,
		"Close": 0.635899,
		"Volume": 54711819
	},
	{
		"Time": "2021-04-05T02:00:00+02:00",
		"Open": 0.718918,
		"High": 0.756201,
		"Low": 0.668791,
		"Close": 0.671811,
		"Volume": 56581633
	},
	{
		"Time": "2021-04-04T02:00:00+02:00",
		"Open": 0.679,
		"High": 0.744044,
		"Low": 0.668931,
		"Close": 0.718918,
		"Volume": 40676448
	},
	{
		"Time": "2021-04-03T02:00:00+02:00",
		"Open": 0.764057,
		"High": 0.765463,
		"Low": 0.675381,
		"Close": 0.679,
		"Volume": 46251791
	},
	{
		"Time": "2021-04-02T02:00:00+02:00",
		"Open": 0.750903,
		"High": 0.781482,
		"Low": 0.72,
		"Close": 0.763852,
		"Volume": 45552367
	},
	{
		"Time": "2021-04-01T02:00:00+02:00",
		"Open": 0.800377,
		"High": 0.80504,
		"Low": 0.735665,
		"Close": 0.750958,
		"Volume": 50167087
	},
	{
		"Time": "2021-03-31T02:00:00+02:00",
		"Open": 0.826976,
		"High": 0.846,
		"Low": 0.722,
		"Close": 0.800699,
		"Volume": 63491099
	},
	{
		"Time": "2021-03-30T02:00:00+02:00",
		"Open": 0.788542,
		"High": 0.855838,
		"Low": 0.773337,
		"Close": 0.82667,
		"Volume": 59014057
	},
	{
		"Time": "2021-03-29T02:00:00+02:00",
		"Open": 0.80882,
		"High": 0.872125,
		"Low": 0.759,
		"Close": 0.789152,
		"Volume": 80105496
	},
	{
		"Time": "2021-03-28T01:00:00+01:00",
		"Open": 0.713229,
		"High": 0.906101,
		"Low": 0.677126,
		"Close": 0.809151,
		"Volume": 174102088
	},
	{
		"Time": "2021-03-27T01:00:00+01:00",
		"Open": 0.619357,
		"High": 0.734715,
		"Low": 0.604507,
		"Close": 0.713202,
		"Volume": 113136759
	},
	{
		"Time": "2021-03-26T01:00:00+01:00",
		"Open": 0.58413,
		"High": 0.625719,
		"Low": 0.569088,
		"Close": 0.619209,
		"Volume": 60409325
	},
	{
		"Time": "2021-03-25T01:00:00+01:00",
		"Open": 0.572122,
		"High": 0.602782,
		"Low": 0.536943,
		"Close": 0.584164,
		"Volume": 76413697
	},
	{
		"Time": "2021-03-24T01:00:00+01:00",
		"Open": 0.567753,
		"High": 0.659999,
		"Low": 0.547645,
		"Close": 0.572594,
		"Volume": 131669131
	},
	{
		"Time": "2021-03-23T01:00:00+01:00",
		"Open": 0.554359,
		"High": 0.592482,
		"Low": 0.509404,
		"Close": 0.566523,
		"Volume": 77156337
	},
	{
		"Time": "2021-03-22T01:00:00+01:00",
		"Open": 0.562955,
		"High": 0.617046,
		"Low": 0.521057,
		"Close": 0.554358,
		"Volume": 99919164
	},
	{
		"Time": "2021-03-21T01:00:00+01:00",
		"Open": 0.536436,
		"High": 0.6,
		"Low": 0.526275,
		"Close": 0.562067,
		"Volume": 66886392
	},
	{
		"Time": "2021-03-20T01:00:00+01:00",
		"Open": 0.604485,
		"High": 0.604738,
		"Low": 0.53578,
		"Close": 0.537369,
		"Volume": 54357034
	},
	{
		"Time": "2021-03-19T01:00:00+01:00",
		"Open": 0.616031,
		"High": 0.623928,
		"Low": 0.5869,
		"Close": 0.603784,
		"Volume": 52667108
	},
	{
		"Time": "2021-03-18T01:00:00+01:00",
		"Open": 0.596967,
		"High": 0.673728,
		"Low": 0.565461,
		"Close": 0.615642,
		"Volume": 137317061
	},
	{
		"Time": "2021-03-17T01:00:00+01:00",
		"Open": 0.591396,
		"High": 0.618252,
		"Low": 0.503547,
		"Close": 0.59546,
		"Volume": 111324266
	},
	{
		"Time": "2021-03-16T01:00:00+01:00",
		"Open": 0.66496,
		"High": 0.68009,
		"Low": 0.566216,
		"Close": 0.592221,
		"Volume": 77335494
	},
	{
		"Time": "2021-03-15T01:00:00+01:00",
		"Open": 0.680142,
		"High": 0.718344,
		"Low": 0.605,
		"Close": 0.666696,
		"Volume": 86742318
	},
	{
		"Time": "2021-03-14T01:00:00+01:00",
		"Open": 0.684997,
		"High": 0.75,
		"Low": 0.645785,
		"Close": 0.680142,
		"Volume": 130467349
	},
	{
		"Time": "2021-03-13T01:00:00+01:00",
		"Open": 0.611328,
		"High": 0.798,
		"Low": 0.549134,
		"Close": 0.684578,
		"Volume": 213498585
	},
	{
		"Time": "2021-03-12T01:00:00+01:00",
		"Open": 0.53,
		"High": 0.63,
		"Low": 0.5161,
		"Close": 0.612668,
		"Volume": 137188524
	},
	{
		"Time": "2021-03-11T01:00:00+01:00",
		"Open": 0.481396,
		"High": 0.564984,
		"Low": 0.471197,
		"Close": 0.53,
		"Volume": 106550679
	},
	{
		"Time": "2021-03-10T01:00:00+01:00",
		"Open": 0.524926,
		"High": 0.526425,
		"Low": 0.451174,
		"Close": 0.481458,
		"Volume": 92923645
	},
	{
		"Time": "2021-03-09T01:00:00+01:00",
		"Open": 0.45947,
		"High": 0.583915,
		"Low": 0.458757,
		"Close": 0.524898,
		"Volume": 212859257
	},
	{
		"Time": "2021-03-08T01:00:00+01:00",
		"Open": 0.379005,
		"High": 0.485,
		"Low": 0.37717,
		"Close": 0.45726,
		"Volume": 150985870
	},
	{
		"Time": "2021-03-07T01:00:00+01:00",
		"Open": 0.343866,
		"High": 0.389997,
		"Low": 0.33817,
		"Close": 0.379207,
		"Volume": 87282379
	},
	{
		"Time": "2021-03-06T01:00:00+01:00",
		"Open": 0.350701,
		"High": 0.368948,
		"Low": 0.316477,
		"Close": 0.343355,
		"Volume": 72068418
	},
	{
		"Time": "2021-03-05T01:00:00+01:00",
		"Open": 0.358617,
		"High": 0.426646,
		"Low": 0.333308,
		"Close": 0.350176,
		"Volume": 225008826
	},
	{
		"Time": "2021-03-04T01:00:00+01:00",
		"Open": 0.307224,
		"High": 0.43257,
		"Low": 0.292899,
		"Close": 0.358,
		"Volume": 307709830
	},
	{
		"Time": "2021-03-03T01:00:00+01:00",
		"Open": 0.25067,
		"High": 0.317433,
		"Low": 0.245936,
		"Close": 0.307819,
		"Volume": 99263544
	},
	{
		"Time": "2021-03-02T01:00:00+01:00",
		"Open": 0.239993,
		"High": 0.26517,
		"Low": 0.2284,
		"Close": 0.251,
		"Volume": 62674884
	},
	{
		"Time": "2021-03-01T01:00:00+01:00",
		"Open": 0.220131,
		"High": 0.245474,
		"Low": 0.215524,
		"Close": 0.24,
		"Volume": 55206595
	},
	{
		"Time": "2021-02-28T01:00:00+01:00",
		"Open": 0.245317,
		"High": 0.266666,
		"Low": 0.199115,
		"Close": 0.220365,
		"Volume": 52400033
	},
	{
		"Time": "2021-02-27T01:00:00+01:00",
		"Open": 0.236002,
		"High": 0.26,
		"Low": 0.234528,
		"Close": 0.245262,
		"Volume": 34531393
	},
	{
		"Time": "2021-02-26T01:00:00+01:00",
		"Open": 0.232817,
		"High": 0.248446,
		"Low": 0.219736,
		"Close": 0.236526,
		"Volume": 53086549
	},
	{
		"Time": "2021-02-25T01:00:00+01:00",
		"Open": 0.247477,
		"High": 0.268555,
		"Low": 0.230193,
		"Close": 0.234036,
		"Volume": 46646166
	},
	{
		"Time": "2021-02-24T01:00:00+01:00",
		"Open": 0.240333,
		"High": 0.271,
		"Low": 0.217852,
		"Close": 0.247599,
		"Volume": 79864137
	},
	{
		"Time": "2021-02-23T01:00:00+01:00",
		"Open": 0.294777,
		"High": 0.3314,
		"Low": 0.173,
		"Close": 0.239755,
		"Volume": 185962826
	},
	{
		"Time": "2021-02-22T01:00:00+01:00",
		"Open": 0.321073,
		"High": 0.368,
		"Low": 0.144339,
		"Close": 0.294752,
		"Volume": 173636306
	},
	{
		"Time": "2021-02-21T01:00:00+01:00",
		"Open": 0.295598,
		"High": 0.35,
		"Low": 0.288548,
		"Close": 0.321073,
		"Volume": 87412400
	},
	{
		"Time": "2021-02-20T01:00:00+01:00",
		"Open": 0.306493,
		"High": 0.325,
		"Low": 0.2733,
		"Close": 0.295598,
		"Volume": 71515839
	},
	{
		"Time": "2021-02-19T01:00:00+01:00",
		"Open": 0.326233,
		"High": 0.328319,
		"Low": 0.271919,
		"Close": 0.306528,
		"Volume": 102618317
	},
	{
		"Time": "2021-02-18T01:00:00+01:00",
		"Open": 0.242224,
		"High": 0.343998,
		"Low": 0.23579,
		"Close": 0.326217,
		"Volume": 236007383
	},
	{
		"Time": "2021-02-17T01:00:00+01:00",
		"Open": 0.230982,
		"High": 0.264013,
		"Low": 0.205567,
		"Close": 0.242085,
		"Volume": 121401661
	},
	{
		"Time": "2021-02-16T01:00:00+01:00",
		"Open": 0.238986,
		"High": 0.249713,
		"Low": 0.216236,
		"Close": 0.231428,
		"Volume": 59535799
	},
	{
		"Time": "2021-02-15T01:00:00+01:00",
		"Open": 0.266666,
		"High": 0.270771,
		"Low": 0.197335,
		"Close": 0.240507,
		"Volume": 148899213
	},
	{
		"Time": "2021-02-14T01:00:00+01:00",
		"Open": 0.206389,
		"High": 0.293,
		"Low": 0.19284,
		"Close": 0.266452,
		"Volume": 485863308
	},
	{
		"Time": "2021-02-13T01:00:00+01:00",
		"Open": 0.163993,
		"High": 0.218,
		"Low": 0.163056,
		"Close": 0.206698,
		"Volume": 204029827
	},
	{
		"Time": "2021-02-12T01:00:00+01:00",
		"Open": 0.160125,
		"High": 0.1698,
		"Low": 0.149,
		"Close": 0.163993,
		"Volume": 68519212
	},
	{
		"Time": "2021-02-11T01:00:00+01:00",
		"Open": 0.146883,
		"High": 0.172,
		"Low": 0.142043,
		"Close": 0.159039,
		"Volume": 140377352
	},
	{
		"Time": "2021-02-10T01:00:00+01:00",
		"Open": 0.153355,
		"High": 0.1598,
		"Low": 0.134,
		"Close": 0.146631,
		"Volume": 87957317
	},
	{
		"Time": "2021-02-09T01:00:00+01:00",
		"Open": 0.141561,
		"High": 0.165,
		"Low": 0.138393,
		"Close": 0.153055,
		"Volume": 92306976
	},
	{
		"Time": "2021-02-08T01:00:00+01:00",
		"Open": 0.126635,
		"High": 0.148,
		"Low": 0.122812,
		"Close": 0.14156,
		"Volume": 156379496
	},
	{
		"Time": "2021-02-07T01:00:00+01:00",
		"Open": 0.130542,
		"High": 0.1345,
		"Low": 0.11024,
		"Close": 0.126635,
		"Volume": 150770204
	},
	{
		"Time": "2021-02-06T01:00:00+01:00",
		"Open": 0.144279,
		"High": 0.15,
		"Low": 0.118333,
		"Close": 0.1305,
		"Volume": 136223093
	},
	{
		"Time": "2021-02-05T01:00:00+01:00",
		"Open": 0.100387,
		"High": 0.15,
		"Low": 0.099092,
		"Close": 0.144279,
		"Volume": 250593325
	},
	{
		"Time": "2021-02-04T01:00:00+01:00",
		"Open": 0.099794,
		"High": 0.1298,
		"Low": 0.091,
		"Close": 0.100407,
		"Volume": 325039140
	},
	{
		"Time": "2021-02-03T01:00:00+01:00",
		"Open": 0.096598,
		"High": 0.102,
		"Low": 0.09284,
		"Close": 0.099793,
		"Volume": 87104673
	},
	{
		"Time": "2021-02-02T01:00:00+01:00",
		"Open": 0.08285,
		"High": 0.103178,
		"Low": 0.082719,
		"Close": 0.096453,
		"Volume": 169284175
	},
	{
		"Time": "2021-02-01T01:00:00+01:00",
		"Open": 0.082917,
		"High": 0.085999,
		"Low": 0.07778,
		"Close": 0.082916,
		"Volume": 59581159
	},
	{
		"Time": "2021-01-31T01:00:00+01:00",
		"Open": 0.087754,
		"High": 0.091426,
		"Low": 0.081,
		"Close": 0.083188,
		"Volume": 49733493
	},
	{
		"Time": "2021-01-30T01:00:00+01:00",
		"Open": 0.088568,
		"High": 0.0941,
		"Low": 0.085001,
		"Close": 0.088099,
		"Volume": 55689380
	},
	{
		"Time": "2021-01-29T01:00:00+01:00",
		"Open": 0.08869,
		"High": 0.09956,
		"Low": 0.0825,
		"Close": 0.088304,
		"Volume": 93373768
	},
	{
		"Time": "2021-01-28T01:00:00+01:00",
		"Open": 0.081225,
		"High": 0.090834,
		"Low": 0.077405,
		"Close": 0.08861,
		"Volume": 82913633
	},
	{
		"Time": "2021-01-27T01:00:00+01:00",
		"Open": 0.093256,
		"High": 0.095999,
		"Low": 0.075479,
		"Close": 0.081225,
		"Volume": 102123765
	},
	{
		"Time": "2021-01-26T01:00:00+01:00",
		"Open": 0.092744,
		"High": 0.0985,
		"Low": 0.08623,
		"Close": 0.09288,
		"Volume": 42483356
	},
	{
		"Time": "2021-01-25T01:00:00+01:00",
		"Open": 0.095256,
		"High": 0.104623,
		"Low": 0.089004,
		"Close": 0.092698,
		"Volume": 76392895
	},
	{
		"Time": "2021-01-24T01:00:00+01:00",
		"Open": 0.101357,
		"High": 0.102992,
		"Low": 0.09182,
		"Close": 0.095259,
		"Volume": 50750256
	},
	{
		"Time": "2021-01-23T01:00:00+01:00",
		"Open": 0.109442,
		"High": 0.111843,
		"Low": 0.096702,
		"Close": 0.101107,
		"Volume": 68485014
	},
	{
		"Time": "2021-01-22T01:00:00+01:00",
		"Open": 0.108483,
		"High": 0.1194,
		"Low": 0.0933,
		"Close": 0.109443,
		"Volume": 171631847
	},
	{
		"Time": "2021-01-21T01:00:00+01:00",
		"Open": 0.053854,
		"High": 0.158809,
		"Low": 0.0505,
		"Close": 0.108487,
		"Volume": 1032182664
	},
	{
		"Time": "2021-01-20T01:00:00+01:00",
		"Open": 0.053913,
		"High": 0.060581,
		"Low": 0.047951,
		"Close": 0.053857,
		"Volume": 94276289
	},
	{
		"Time": "2021-01-19T01:00:00+01:00",
		"Open": 0.052089,
		"High": 0.058,
		"Low": 0.049797,
		"Close": 0.053712,
		"Volume": 92974643
	},
	{
		"Time": "2021-01-18T01:00:00+01:00",
		"Open": 0.051154,
		"High": 0.0545,
		"Low": 0.048,
		"Close": 0.05209,
		"Volume": 65011522
	},
	{
		"Time": "2021-01-17T01:00:00+01:00",
		"Open": 0.043901,
		"High": 0.053,
		"Low": 0.042101,
		"Close": 0.051041,
		"Volume": 134165835
	},
	{
		"Time": "2021-01-16T01:00:00+01:00",
		"Open": 0.044109,
		"High": 0.047,
		"Low": 0.042538,
		"Close": 0.04395,
		"Volume": 53233491
	},
	{
		"Time": "2021-01-15T01:00:00+01:00",
		"Open": 0.040894,
		"High": 0.04622,
		"Low": 0.039909,
		"Close": 0.043995,
		"Volume": 61544692
	},
	{
		"Time": "2021-01-14T01:00:00+01:00",
		"Open": 0.040523,
		"High": 0.0422,
		"Low": 0.039448,
		"Close": 0.040896,
		"Volume": 25480252
	},
	{
		"Time": "2021-01-13T01:00:00+01:00",
		"Open": 0.037903,
		"High": 0.0415,
		"Low": 0.036746,
		"Close": 0.040724,
		"Volume": 27437962
	},
	{
		"Time": "2021-01-12T01:00:00+01:00",
		"Open": 0.040501,
		"High": 0.040957,
		"Low": 0.036501,
		"Close": 0.037904,
		"Volume": 30698085
	},
	{
		"Time": "2021-01-11T01:00:00+01:00",
		"Open": 0.04235,
		"High": 0.04245,
		"Low": 0.03455,
		"Close": 0.040616,
		"Volume": 51001503
	},
	{
		"Time": "2021-01-10T01:00:00+01:00",
		"Open": 0.045937,
		"High": 0.046634,
		"Low": 0.040699,
		"Close": 0.04238,
		"Volume": 44380353
	},
	{
		"Time": "2021-01-09T01:00:00+01:00",
		"Open": 0.043285,
		"High": 0.047491,
		"Low": 0.04175,
		"Close": 0.045938,
		"Volume": 49103494
	},
	{
		"Time": "2021-01-08T01:00:00+01:00",
		"Open": 0.043573,
		"High": 0.04715,
		"Low": 0.040601,
		"Close": 0.043303,
		"Volume": 84682300
	},
	{
		"Time": "2021-01-07T01:00:00+01:00",
		"Open": 0.044629,
		"High": 0.046622,
		"Low": 0.041,
		"Close": 0.043391,
		"Volume": 63937202
	},
	{
		"Time": "2021-01-06T01:00:00+01:00",
		"Open": 0.0417,
		"High": 0.047721,
		"Low": 0.040832,
		"Close": 0.044655,
		"Volume": 85860022
	},
	{
		"Time": "2021-01-05T01:00:00+01:00",
		"Open": 0.040432,
		"High": 0.045,
		"Low": 0.039,
		"Close": 0.0417,
		"Volume": 67010639
	},
	{
		"Time": "2021-01-04T01:00:00+01:00",
		"Open": 0.040936,
		"High": 0.043,
		"Low": 0.0361,
		"Close": 0.040432,
		"Volume": 43625078
	},
	{
		"Time": "2021-01-03T01:00:00+01:00",
		"Open": 0.038161,
		"High": 0.0415,
		"Low": 0.036866,
		"Close": 0.040928,
		"Volume": 39392323
	},
	{
		"Time": "2021-01-02T01:00:00+01:00",
		"Open": 0.036973,
		"High": 0.039546,
		"Low": 0.036414,
		"Close": 0.038107,
		"Volume": 29435281
	},
	{
		"Time": "2021-01-01T01:00:00+01:00",
		"Open": 0.035571,
		"High": 0.039009,
		"Low": 0.0351,
		"Close": 0.036973,
		"Volume": 22342660
	},
	{
		"Time": "2020-12-31T01:00:00+01:00",
		"Open": 0.036167,
		"High": 0.036333,
		"Low": 0.034011,
		"Close": 0.0357,
		"Volume": 20620192
	},
	{
		"Time": "2020-12-30T01:00:00+01:00",
		"Open": 0.037259,
		"High": 0.038251,
		"Low": 0.035715,
		"Close": 0.036165,
		"Volume": 20496178
	},
	{
		"Time": "2020-12-29T01:00:00+01:00",
		"Open": 0.039032,
		"High": 0.040126,
		"Low": 0.034768,
		"Close": 0.03726,
		"Volume": 45319985
	},
	{
		"Time": "2020-12-28T01:00:00+01:00",
		"Open": 0.039476,
		"High": 0.04165,
		"Low": 0.0385,
		"Close": 0.038948,
		"Volume": 31324074
	},
	{
		"Time": "2020-12-27T01:00:00+01:00",
		"Open": 0.037966,
		"High": 0.042042,
		"Low": 0.035657,
		"Close": 0.039317,
		"Volume": 42505928
	},
	{
		"Time": "2020-12-26T01:00:00+01:00",
		"Open": 0.039024,
		"High": 0.04043,
		"Low": 0.037092,
		"Close": 0.03787,
		"Volume": 30236160
	},
	{
		"Time": "2020-12-25T01:00:00+01:00",
		"Open": 0.040155,
		"High": 0.042151,
		"Low": 0.037992,
		"Close": 0.039027,
		"Volume": 28510522
	},
	{
		"Time": "2020-12-24T01:00:00+01:00",
		"Open": 0.038166,
		"High": 0.040849,
		"Low": 0.035569,
		"Close": 0.04043,
		"Volume": 42199309
	},
	{
		"Time": "2020-12-23T01:00:00+01:00",
		"Open": 0.046391,
		"High": 0.046789,
		"Low": 0.0356,
		"Close": 0.038166,
		"Volume": 63062655
	},
	{
		"Time": "2020-12-22T01:00:00+01:00",
		"Open": 0.047545,
		"High": 0.049,
		"Low": 0.041887,
		"Close": 0.046458,
		"Volume": 59106904
	},
	{
		"Time": "2020-12-21T01:00:00+01:00",
		"Open": 0.04968,
		"High": 0.051148,
		"Low": 0.04511,
		"Close": 0.047547,
		"Volume": 49050860
	},
	{
		"Time": "2020-12-20T01:00:00+01:00",
		"Open": 0.051351,
		"High": 0.0558,
		"Low": 0.048999,
		"Close": 0.049698,
		"Volume": 88334060
	},
	{
		"Time": "2020-12-19T01:00:00+01:00",
		"Open": 0.051166,
		"High": 0.053,
		"Low": 0.04893,
		"Close": 0.051501,
		"Volume": 55645758
	},
	{
		"Time": "2020-12-18T01:00:00+01:00",
		"Open": 0.049086,
		"High": 0.05199,
		"Low": 0.0473,
		"Close": 0.051348,
		"Volume": 40945811
	},
	{
		"Time": "2020-12-17T01:00:00+01:00",
		"Open": 0.051928,
		"High": 0.052605,
		"Low": 0.048548,
		"Close": 0.049086,
		"Volume": 54517582
	},
	{
		"Time": "2020-12-16T01:00:00+01:00",
		"Open": 0.052523,
		"High": 0.053653,
		"Low": 0.048411,
		"Close": 0.051928,
		"Volume": 60036397
	},
	{
		"Time": "2020-12-15T01:00:00+01:00",
		"Open": 0.049802,
		"High": 0.0534,
		"Low": 0.04777,
		"Close": 0.052572,
		"Volume": 39377151
	},
	{
		"Time": "2020-12-14T01:00:00+01:00",
		"Open": 0.048305,
		"High": 0.052191,
		"Low": 0.047,
		"Close": 0.049702,
		"Volume": 31733741
	},
	{
		"Time": "2020-12-13T01:00:00+01:00",
		"Open": 0.047502,
		"High": 0.05,
		"Low": 0.046,
		"Close": 0.048302,
		"Volume": 28228653
	},
	{
		"Time": "2020-12-12T01:00:00+01:00",
		"Open": 0.045329,
		"High": 0.05053,
		"Low": 0.045097,
		"Close": 0.047621,
		"Volume": 46962485
	},
	{
		"Time": "2020-12-11T01:00:00+01:00",
		"Open": 0.052642,
		"High": 0.054192,
		"Low": 0.045,
		"Close": 0.045332,
		"Volume": 59915032
	},
	{
		"Time": "2020-12-10T01:00:00+01:00",
		"Open": 0.0525,
		"High": 0.0562,
		"Low": 0.0488,
		"Close": 0.052642,
		"Volume": 135183601
	},
	{
		"Time": "2020-12-09T01:00:00+01:00",
		"Open": 0.044536,
		"High": 0.054,
		"Low": 0.04049,
		"Close": 0.052499,
		"Volume": 91756693
	},
	{
		"Time": "2020-12-08T01:00:00+01:00",
		"Open": 0.045222,
		"High": 0.049,
		"Low": 0.043727,
		"Close": 0.044512,
		"Volume": 55451861
	},
	{
		"Time": "2020-12-07T01:00:00+01:00",
		"Open": 0.043237,
		"High": 0.047215,
		"Low": 0.042536,
		"Close": 0.045369,
		"Volume": 29270534
	},
	{
		"Time": "2020-12-06T01:00:00+01:00",
		"Open": 0.043548,
		"High": 0.045277,
		"Low": 0.042517,
		"Close": 0.043247,
		"Volume": 11573059
	},
	{
		"Time": "2020-12-05T01:00:00+01:00",
		"Open": 0.041901,
		"High": 0.044324,
		"Low": 0.041065,
		"Close": 0.043547,
		"Volume": 20893903
	},
	{
		"Time": "2020-12-04T01:00:00+01:00",
		"Open": 0.046601,
		"High": 0.046999,
		"Low": 0.041901,
		"Close": 0.041902,
		"Volume": 24512212
	},
	{
		"Time": "2020-12-03T01:00:00+01:00",
		"Open": 0.047001,
		"High": 0.047975,
		"Low": 0.045869,
		"Close": 0.046771,
		"Volume": 20575699
	},
	{
		"Time": "2020-12-02T01:00:00+01:00",
		"Open": 0.04579,
		"High": 0.049084,
		"Low": 0.04389,
		"Close": 0.046973,
		"Volume": 30892181
	},
	{
		"Time": "2020-12-01T01:00:00+01:00",
		"Open": 0.04825,
		"High": 0.048671,
		"Low": 0.04321,
		"Close": 0.045813,
		"Volume": 30771745
	},
	{
		"Time": "2020-11-30T01:00:00+01:00",
		"Open": 0.045569,
		"High": 0.0495,
		"Low": 0.044861,
		"Close": 0.048467,
		"Volume": 30618508
	},
	{
		"Time": "2020-11-29T01:00:00+01:00",
		"Open": 0.044886,
		"High": 0.045983,
		"Low": 0.043101,
		"Close": 0.04557,
		"Volume": 20726093
	},
	{
		"Time": "2020-11-28T01:00:00+01:00",
		"Open": 0.045631,
		"High": 0.046666,
		"Low": 0.042909,
		"Close": 0.044599,
		"Volume": 40998176
	},
	{
		"Time": "2020-11-27T01:00:00+01:00",
		"Open": 0.041447,
		"High": 0.046499,
		"Low": 0.038957,
		"Close": 0.045639,
		"Volume": 32790089
	},
	{
		"Time": "2020-11-26T01:00:00+01:00",
		"Open": 0.044967,
		"High": 0.0475,
		"Low": 0.037,
		"Close": 0.041443,
		"Volume": 57321170
	},
	{
		"Time": "2020-11-25T01:00:00+01:00",
		"Open": 0.045668,
		"High": 0.0528,
		"Low": 0.042768,
		"Close": 0.045213,
		"Volume": 75441900
	},
	{
		"Time": "2020-11-24T01:00:00+01:00",
		"Open": 0.047579,
		"High": 0.050576,
		"Low": 0.0451,
		"Close": 0.04537,
		"Volume": 87365743
	},
	{
		"Time": "2020-11-23T01:00:00+01:00",
		"Open": 0.04508,
		"High": 0.061699,
		"Low": 0.041777,
		"Close": 0.047761,
		"Volume": 231395104
	},
	{
		"Time": "2020-11-22T01:00:00+01:00",
		"Open": 0.040285,
		"High": 0.049999,
		"Low": 0.035545,
		"Close": 0.04509,
		"Volume": 140161801
	},
	{
		"Time": "2020-11-21T01:00:00+01:00",
		"Open": 0.03637,
		"High": 0.041,
		"Low": 0.036123,
		"Close": 0.04022,
		"Volume": 31608195
	},
	{
		"Time": "2020-11-20T01:00:00+01:00",
		"Open": 0.0356,
		"High": 0.037692,
		"Low": 0.0356,
		"Close": 0.036371,
		"Volume": 23053362
	},
	{
		"Time": "2020-11-19T01:00:00+01:00",
		"Open": 0.035559,
		"High": 0.037351,
		"Low": 0.035002,
		"Close": 0.0356,
		"Volume": 20733411
	},
	{
		"Time": "2020-11-18T01:00:00+01:00",
		"Open": 0.037231,
		"High": 0.037571,
		"Low": 0.033918,
		"Close": 0.035559,
		"Volume": 25365204
	},
	{
		"Time": "2020-11-17T01:00:00+01:00",
		"Open": 0.03874,
		"High": 0.03918,
		"Low": 0.036269,
		"Close": 0.037231,
		"Volume": 30148979
	},
	{
		"Time": "2020-11-16T01:00:00+01:00",
		"Open": 0.037722,
		"High": 0.039276,
		"Low": 0.037276,
		"Close": 0.038599,
		"Volume": 28255141
	},
	{
		"Time": "2020-11-15T01:00:00+01:00",
		"Open": 0.0384,
		"High": 0.040631,
		"Low": 0.037098,
		"Close": 0.037568,
		"Volume": 37853985
	},
	{
		"Time": "2020-11-14T01:00:00+01:00",
		"Open": 0.039126,
		"High": 0.039827,
		"Low": 0.036911,
		"Close": 0.038406,
		"Volume": 22177158
	},
	{
		"Time": "2020-11-13T01:00:00+01:00",
		"Open": 0.0388,
		"High": 0.04174,
		"Low": 0.038315,
		"Close": 0.039069,
		"Volume": 61583264
	},
	{
		"Time": "2020-11-12T01:00:00+01:00",
		"Open": 0.042651,
		"High": 0.055695,
		"Low": 0.038126,
		"Close": 0.038925,
		"Volume": 164181816
	},
	{
		"Time": "2020-11-11T01:00:00+01:00",
		"Open": 0.041589,
		"High": 0.0439,
		"Low": 0.040177,
		"Close": 0.042673,
		"Volume": 35755846
	},
	{
		"Time": "2020-11-10T01:00:00+01:00",
		"Open": 0.037928,
		"High": 0.042444,
		"Low": 0.037775,
		"Close": 0.041591,
		"Volume": 35084215
	},
	{
		"Time": "2020-11-09T01:00:00+01:00",
		"Open": 0.037997,
		"High": 0.0399,
		"Low": 0.036,
		"Close": 0.038,
		"Volume": 25723459
	},
	{
		"Time": "2020-11-08T01:00:00+01:00",
		"Open": 0.036344,
		"High": 0.0387,
		"Low": 0.035155,
		"Close": 0.038101,
		"Volume": 20153921
	},
	{
		"Time": "2020-11-07T01:00:00+01:00",
		"Open": 0.037588,
		"High": 0.041,
		"Low": 0.0342,
		"Close": 0.036371,
		"Volume": 46177560
	},
	{
		"Time": "2020-11-06T01:00:00+01:00",
		"Open": 0.034082,
		"High": 0.0385,
		"Low": 0.033742,
		"Close": 0.037389,
		"Volume": 28402753
	},
	{
		"Time": "2020-11-05T01:00:00+01:00",
		"Open": 0.0317,
		"High": 0.037659,
		"Low": 0.0315,
		"Close": 0.03395,
		"Volume": 64945569
	},
	{
		"Time": "2020-11-04T01:00:00+01:00",
		"Open": 0.030899,
		"High": 0.031868,
		"Low": 0.0288,
		"Close": 0.031748,
		"Volume": 31990712
	},
	{
		"Time": "2020-11-03T01:00:00+01:00",
		"Open": 0.035299,
		"High": 0.035299,
		"Low": 0.03,
		"Close": 0.0309,
		"Volume": 33819445
	},
	{
		"Time": "2020-11-02T01:00:00+01:00",
		"Open": 0.035537,
		"High": 0.036258,
		"Low": 0.0335,
		"Close": 0.035299,
		"Volume": 14739815
	},
	{
		"Time": "2020-11-01T01:00:00+01:00",
		"Open": 0.035396,
		"High": 0.036399,
		"Low": 0.034644,
		"Close": 0.03559,
		"Volume": 12687912
	},
	{
		"Time": "2020-10-31T01:00:00+01:00",
		"Open": 0.03566,
		"High": 0.037,
		"Low": 0.0345,
		"Close": 0.035404,
		"Volume": 11711229
	},
	{
		"Time": "2020-10-30T01:00:00+01:00",
		"Open": 0.03768,
		"High": 0.038995,
		"Low": 0.034,
		"Close": 0.035667,
		"Volume": 35494804
	},
	{
		"Time": "2020-10-29T01:00:00+01:00",
		"Open": 0.035284,
		"High": 0.039385,
		"Low": 0.033048,
		"Close": 0.037442,
		"Volume": 35924279
	},
	{
		"Time": "2020-10-28T01:00:00+01:00",
		"Open": 0.037975,
		"High": 0.038501,
		"Low": 0.034166,
		"Close": 0.035184,
		"Volume": 38025660
	},
	{
		"Time": "2020-10-27T01:00:00+01:00",
		"Open": 0.037815,
		"High": 0.039066,
		"Low": 0.03755,
		"Close": 0.0378,
		"Volume": 14271594
	},
	{
		"Time": "2020-10-26T01:00:00+01:00",
		"Open": 0.039301,
		"High": 0.041469,
		"Low": 0.037312,
		"Close": 0.037814,
		"Volume": 28051156
	},
	{
		"Time": "2020-10-25T02:00:00+02:00",
		"Open": 0.040598,
		"High": 0.040948,
		"Low": 0.038295,
		"Close": 0.0393,
		"Volume": 21727506
	},
	{
		"Time": "2020-10-24T02:00:00+02:00",
		"Open": 0.039934,
		"High": 0.0425,
		"Low": 0.039851,
		"Close": 0.0406,
		"Volume": 16822639
	},
	{
		"Time": "2020-10-23T02:00:00+02:00",
		"Open": 0.039938,
		"High": 0.043,
		"Low": 0.038757,
		"Close": 0.039934,
		"Volume": 39390744
	},
	{
		"Time": "2020-10-22T02:00:00+02:00",
		"Open": 0.038333,
		"High": 0.041714,
		"Low": 0.038263,
		"Close": 0.039938,
		"Volume": 26718518
	},
	{
		"Time": "2020-10-21T02:00:00+02:00",
		"Open": 0.038826,
		"High": 0.039586,
		"Low": 0.036537,
		"Close": 0.038333,
		"Volume": 34851076
	},
	{
		"Time": "2020-10-20T02:00:00+02:00",
		"Open": 0.040597,
		"High": 0.041791,
		"Low": 0.038029,
		"Close": 0.038877,
		"Volume": 25381518
	},
	{
		"Time": "2020-10-19T02:00:00+02:00",
		"Open": 0.042627,
		"High": 0.04389,
		"Low": 0.0405,
		"Close": 0.040597,
		"Volume": 30121217
	},
	{
		"Time": "2020-10-18T02:00:00+02:00",
		"Open": 0.04315,
		"High": 0.043551,
		"Low": 0.042144,
		"Close": 0.04248,
		"Volume": 12064199
	},
	{
		"Time": "2020-10-17T02:00:00+02:00",
		"Open": 0.043444,
		"High": 0.044284,
		"Low": 0.042571,
		"Close": 0.043076,
		"Volume": 11435390
	},
	{
		"Time": "2020-10-16T02:00:00+02:00",
		"Open": 0.044808,
		"High": 0.045041,
		"Low": 0.040734,
		"Close": 0.043514,
		"Volume": 27073932
	},
	{
		"Time": "2020-10-15T02:00:00+02:00",
		"Open": 0.045755,
		"High": 0.0462,
		"Low": 0.044052,
		"Close": 0.044915,
		"Volume": 11428312
	},
	{
		"Time": "2020-10-14T02:00:00+02:00",
		"Open": 0.04635,
		"High": 0.047102,
		"Low": 0.045,
		"Close": 0.045985,
		"Volume": 16665532
	},
	{
		"Time": "2020-10-13T02:00:00+02:00",
		"Open": 0.047318,
		"High": 0.049286,
		"Low": 0.045387,
		"Close": 0.046367,
		"Volume": 26356115
	},
	{
		"Time": "2020-10-12T02:00:00+02:00",
		"Open": 0.048611,
		"High": 0.050492,
		"Low": 0.0464,
		"Close": 0.047317,
		"Volume": 35294513
	},
	{
		"Time": "2020-10-11T02:00:00+02:00",
		"Open": 0.0456,
		"High": 0.049659,
		"Low": 0.045158,
		"Close": 0.048887,
		"Volume": 22970830
	},
	{
		"Time": "2020-10-10T02:00:00+02:00",
		"Open": 0.049699,
		"High": 0.051527,
		"Low": 0.0452,
		"Close": 0.045802,
		"Volume": 39441533
	},
	{
		"Time": "2020-10-09T02:00:00+02:00",
		"Open": 0.047947,
		"High": 0.050422,
		"Low": 0.0459,
		"Close": 0.049704,
		"Volume": 23636082
	},
	{
		"Time": "2020-10-08T02:00:00+02:00",
		"Open": 0.045457,
		"High": 0.048,
		"Low": 0.043,
		"Close": 0.047717,
		"Volume": 18228183
	},
	{
		"Time": "2020-10-07T02:00:00+02:00",
		"Open": 0.046645,
		"High": 0.04676,
		"Low": 0.042533,
		"Close": 0.045407,
		"Volume": 20601821
	},
	{
		"Time": "2020-10-06T02:00:00+02:00",
		"Open": 0.050897,
		"High": 0.050916,
		"Low": 0.045673,
		"Close": 0.046363,
		"Volume": 45825504
	},
	{
		"Time": "2020-10-05T02:00:00+02:00",
		"Open": 0.048398,
		"High": 0.054528,
		"Low": 0.04709,
		"Close": 0.050897,
		"Volume": 79367204
	},
	{
		"Time": "2020-10-04T02:00:00+02:00",
		"Open": 0.045284,
		"High": 0.04888,
		"Low": 0.042209,
		"Close": 0.0486,
		"Volume": 45636836
	},
	{
		"Time": "2020-10-03T02:00:00+02:00",
		"Open": 0.040925,
		"High": 0.047244,
		"Low": 0.040838,
		"Close": 0.045291,
		"Volume": 47591080
	},
	{
		"Time": "2020-10-02T02:00:00+02:00",
		"Open": 0.042427,
		"High": 0.04345,
		"Low": 0.039133,
		"Close": 0.040925,
		"Volume": 30274129
	},
	{
		"Time": "2020-10-01T02:00:00+02:00",
		"Open": 0.046153,
		"High": 0.046785,
		"Low": 0.041,
		"Close": 0.042427,
		"Volume": 33640492
	},
	{
		"Time": "2020-09-30T02:00:00+02:00",
		"Open": 0.043586,
		"High": 0.04806,
		"Low": 0.042102,
		"Close": 0.046153,
		"Volume": 60182366
	},
	{
		"Time": "2020-09-29T02:00:00+02:00",
		"Open": 0.041611,
		"High": 0.044,
		"Low": 0.041324,
		"Close": 0.043586,
		"Volume": 26164860
	},
	{
		"Time": "2020-09-28T02:00:00+02:00",
		"Open": 0.043157,
		"High": 0.0457,
		"Low": 0.040714,
		"Close": 0.041611,
		"Volume": 52291820
	},
	{
		"Time": "2020-09-27T02:00:00+02:00",
		"Open": 0.0464,
		"High": 0.046494,
		"Low": 0.0411,
		"Close": 0.04324,
		"Volume": 64324503
	},
	{
		"Time": "2020-09-26T02:00:00+02:00",
		"Open": 0.048392,
		"High": 0.0489,
		"Low": 0.045313,
		"Close": 0.046543,
		"Volume": 34526641
	},
	{
		"Time": "2020-09-25T02:00:00+02:00",
		"Open": 0.04782,
		"High": 0.05012,
		"Low": 0.0456,
		"Close": 0.048397,
		"Volume": 69028105
	},
	{
		"Time": "2020-09-24T02:00:00+02:00",
		"Open": 0.042752,
		"High": 0.051,
		"Low": 0.042346,
		"Close": 0.047824,
		"Volume": 134291939
	},
	{
		"Time": "2020-09-23T02:00:00+02:00",
		"Open": 0.043737,
		"High": 0.0495,
		"Low": 0.041102,
		"Close": 0.042729,
		"Volume": 127165767
	},
	{
		"Time": "2020-09-22T02:00:00+02:00",
		"Open": 0.0384,
		"High": 0.044767,
		"Low": 0.036306,
		"Close": 0.043864,
		"Volume": 52209615
	},
	{
		"Time": "2020-09-21T02:00:00+02:00",
		"Open": 0.042938,
		"High": 0.044698,
		"Low": 0.0362,
		"Close": 0.0384,
		"Volume": 49730131
	},
	{
		"Time": "2020-09-20T02:00:00+02:00",
		"Open": 0.047238,
		"High": 0.0482,
		"Low": 0.04221,
		"Close": 0.042968,
		"Volume": 27533136
	},
	{
		"Time": "2020-09-19T02:00:00+02:00",
		"Open": 0.043959,
		"High": 0.048634,
		"Low": 0.042403,
		"Close": 0.047105,
		"Volume": 41934004
	},
	{
		"Time": "2020-09-18T02:00:00+02:00",
		"Open": 0.043831,
		"High": 0.047244,
		"Low": 0.042916,
		"Close": 0.04396,
		"Volume": 38918564
	},
	{
		"Time": "2020-09-17T02:00:00+02:00",
		"Open": 0.044495,
		"High": 0.046934,
		"Low": 0.042389,
		"Close": 0.043889,
		"Volume": 28267299
	},
	{
		"Time": "2020-09-16T02:00:00+02:00",
		"Open": 0.042217,
		"High": 0.049948,
		"Low": 0.040401,
		"Close": 0.044171,
		"Volume": 52313451
	},
	{
		"Time": "2020-09-15T02:00:00+02:00",
		"Open": 0.046317,
		"High": 0.050855,
		"Low": 0.042,
		"Close": 0.042201,
		"Volume": 74584125
	},
	{
		"Time": "2020-09-14T02:00:00+02:00",
		"Open": 0.043632,
		"High": 0.047679,
		"Low": 0.04114,
		"Close": 0.04635,
		"Volume": 55021437
	},
	{
		"Time": "2020-09-13T02:00:00+02:00",
		"Open": 0.049104,
		"High": 0.0499,
		"Low": 0.0416,
		"Close": 0.043521,
		"Volume": 51335182
	},
	{
		"Time": "2020-09-12T02:00:00+02:00",
		"Open": 0.05151,
		"High": 0.05151,
		"Low": 0.047255,
		"Close": 0.049368,
		"Volume": 43012168
	},
	{
		"Time": "2020-09-11T02:00:00+02:00",
		"Open": 0.04948,
		"High": 0.055,
		"Low": 0.046307,
		"Close": 0.05151,
		"Volume": 93726866
	},
	{
		"Time": "2020-09-10T02:00:00+02:00",
		"Open": 0.048209,
		"High": 0.053525,
		"Low": 0.047,
		"Close": 0.049487,
		"Volume": 102235982
	},
	{
		"Time": "2020-09-09T02:00:00+02:00",
		"Open": 0.049572,
		"High": 0.0568,
		"Low": 0.046201,
		"Close": 0.048208,
		"Volume": 203073037
	},
	{
		"Time": "2020-09-08T02:00:00+02:00",
		"Open": 0.038819,
		"High": 0.058454,
		"Low": 0.0369,
		"Close": 0.049601,
		"Volume": 256418605
	},
	{
		"Time": "2020-09-07T02:00:00+02:00",
		"Open": 0.04089,
		"High": 0.041188,
		"Low": 0.033514,
		"Close": 0.038956,
		"Volume": 43860658
	},
	{
		"Time": "2020-09-06T02:00:00+02:00",
		"Open": 0.037527,
		"High": 0.042656,
		"Low": 0.033259,
		"Close": 0.040949,
		"Volume": 58413360
	},
	{
		"Time": "2020-09-05T02:00:00+02:00",
		"Open": 0.044907,
		"High": 0.047,
		"Low": 0.035004,
		"Close": 0.037527,
		"Volume": 65244909
	},
	{
		"Time": "2020-09-04T02:00:00+02:00",
		"Open": 0.043887,
		"High": 0.047495,
		"Low": 0.037401,
		"Close": 0.044869,
		"Volume": 73165446
	},
	{
		"Time": "2020-09-03T02:00:00+02:00",
		"Open": 0.058302,
		"High": 0.0595,
		"Low": 0.043419,
		"Close": 0.043681,
		"Volume": 84224482
	},
	{
		"Time": "2020-09-02T02:00:00+02:00",
		"Open": 0.059794,
		"High": 0.0608,
		"Low": 0.050843,
		"Close": 0.0583,
		"Volume": 97783959
	},
	{
		"Time": "2020-09-01T02:00:00+02:00",
		"Open": 0.070005,
		"High": 0.070898,
		"Low": 0.0593,
		"Close": 0.059799,
		"Volume": 130753976
	},
	{
		"Time": "2020-08-31T02:00:00+02:00",
		"Open": 0.0669,
		"High": 0.078467,
		"Low": 0.0669,
		"Close": 0.070005,
		"Volume": 114062160
	},
	{
		"Time": "2020-08-30T02:00:00+02:00",
		"Open": 0.072765,
		"High": 0.0738,
		"Low": 0.0646,
		"Close": 0.066653,
		"Volume": 77047896
	},
	{
		"Time": "2020-08-29T02:00:00+02:00",
		"Open": 0.069828,
		"High": 0.0745,
		"Low": 0.065112,
		"Close": 0.072767,
		"Volume": 91906481
	},
	{
		"Time": "2020-08-28T02:00:00+02:00",
		"Open": 0.074221,
		"High": 0.0825,
		"Low": 0.068501,
		"Close": 0.069976,
		"Volume": 206290561
	},
	{
		"Time": "2020-08-27T02:00:00+02:00",
		"Open": 0.058509,
		"High": 0.075526,
		"Low": 0.054183,
		"Close": 0.073953,
		"Volume": 268039013
	},
	{
		"Time": "2020-08-26T02:00:00+02:00",
		"Open": 0.04805,
		"High": 0.058689,
		"Low": 0.046896,
		"Close": 0.058571,
		"Volume": 78970460
	},
	{
		"Time": "2020-08-25T02:00:00+02:00",
		"Open": 0.051232,
		"High": 0.05675,
		"Low": 0.045,
		"Close": 0.048002,
		"Volume": 74226864
	},
	{
		"Time": "2020-08-24T02:00:00+02:00",
		"Open": 0.043652,
		"High": 0.053749,
		"Low": 0.042063,
		"Close": 0.050735,
		"Volume": 74190522
	},
	{
		"Time": "2020-08-23T02:00:00+02:00",
		"Open": 0.045973,
		"High": 0.048323,
		"Low": 0.041793,
		"Close": 0.043611,
		"Volume": 32322297
	},
	{
		"Time": "2020-08-22T02:00:00+02:00",
		"Open": 0.044231,
		"High": 0.0491,
		"Low": 0.040202,
		"Close": 0.045973,
		"Volume": 55057194
	},
	{
		"Time": "2020-08-21T02:00:00+02:00",
		"Open": 0.05387,
		"High": 0.05387,
		"Low": 0.044005,
		"Close": 0.04425,
		"Volume": 67549095
	},
	{
		"Time": "2020-08-20T02:00:00+02:00",
		"Open": 0.052519,
		"High": 0.057332,
		"Low": 0.05076,
		"Close": 0.053483,
		"Volume": 67304708
	},
	{
		"Time": "2020-08-19T02:00:00+02:00",
		"Open": 0.05141,
		"High": 0.0571,
		"Low": 0.048,
		"Close": 0.051942,
		"Volume": 76398711
	},
	{
		"Time": "2020-08-18T02:00:00+02:00",
		"Open": 0.053813,
		"High": 0.061052,
		"Low": 0.050205,
		"Close": 0.051631,
		"Volume": 80926224
	},
	{
		"Time": "2020-08-17T02:00:00+02:00",
		"Open": 0.060853,
		"High": 0.065199,
		"Low": 0.052345,
		"Close": 0.053812,
		"Volume": 106548486
	},
	{
		"Time": "2020-08-16T02:00:00+02:00",
		"Open": 0.051413,
		"High": 0.070027,
		"Low": 0.048,
		"Close": 0.060852,
		"Volume": 295461524
	},
	{
		"Time": "2020-08-15T02:00:00+02:00",
		"Open": 0.065817,
		"High": 0.070869,
		"Low": 0.049,
		"Close": 0.051101,
		"Volume": 372663272
	},
	{
		"Time": "2020-08-14T02:00:00+02:00",
		"Open": 0.008333,
		"High": 0.09471,
		"Low": 0.008333,
		"Close": 0.065997,
		"Volume": 989575855
	}
]